error_translator/__init__.py
error_translator/error_translator.py
error_translator/models/__init__.py
error_translator/models/base_model.py
error_translator/models/huggingface_model.py
error_translator/models/local_huggingface_model.py
error_translator/models/openai_model.py
error_translator-0.1.5.dist-info/METADATA
error_translator-0.1.5.dist-info/WHEEL
error_translator-0.1.5.dist-info/top_level.txt
error_translator-0.1.5.dist-info/RECORD
