Metadata-Version: 2.4
Name: error_translator
Version: 0.1.5
Summary: Translate Python errors into AI-explained suggestions.
Author-email: Romas Laužadis <rromikas@gmail.com>
License: MIT
Project-URL: Homepage, https://github.com/rromikas/error_translator
Requires-Python: >=3.7
Requires-Dist: rich
Requires-Dist: python-dotenv
Requires-Dist: transformers
Requires-Dist: openai
